_xtimeout.cp36-win32.pdb
_xtimeout.cp36-win32.pyd
xtimeout/__init__.py
xtimeout/tests/__init__.py
xtimeout/tests/test_monitor.py
xtimeout-0.2.0.dist-info/METADATA
xtimeout-0.2.0.dist-info/RECORD
xtimeout-0.2.0.dist-info/WHEEL
xtimeout-0.2.0.dist-info/top_level.txt
