Metadata-Version: 2.1
Name: xtimeout
Version: 0.2.0
Summary: Trace a timeout function call and handle with it
Home-page: https://github.com/amos402/py-xtimeout
Author: amos402
Author-email: amos_402@msn.com
License: MIT
Keywords: timeout,inject,timeout handler,function timetout
Platform: UNKNOWN
Classifier: License :: OSI Approved :: MIT License
Classifier: Programming Language :: C++
Classifier: Programming Language :: Python :: 3 :: Only
Classifier: Programming Language :: Python
